.DS_Store
autotab/__init__.py
autotab/api_client.py
autotab/api_response.py
autotab/configuration.py
autotab/exceptions.py
autotab/py.typed
autotab/rest.py
autotab/api/__init__.py
autotab/api/run_api.py
autotab/api/skill_api.py
autotab/models/__init__.py
autotab/models/environment.py
autotab/models/http_validation_error.py
autotab/models/input.py
autotab/models/run_session.py
autotab/models/run_session_state.py
autotab/models/run_session_with_data.py
autotab/models/run_skill_request.py
autotab/models/skill.py
autotab/models/validation_error.py
autotab/models/validation_error_loc_inner.py
autotab/models/variable_data_type.py
autotab_ai-0.0.5.dist-info/LICENSE
autotab_ai-0.0.5.dist-info/METADATA
autotab_ai-0.0.5.dist-info/WHEEL
autotab_ai-0.0.5.dist-info/top_level.txt
autotab_ai-0.0.5.dist-info/RECORD
